moducomp/__init__.py
moducomp/cli.py
moducomp-0.6.0.dist-info/METADATA
moducomp-0.6.0.dist-info/WHEEL
moducomp-0.6.0.dist-info/entry_points.txt
moducomp-0.6.0.dist-info/licenses/LICENSE.txt
moducomp-0.6.0.dist-info/RECORD
