Metadata-Version: 2.4
Name: moducomp
Version: 0.6.0
Summary: moducomp for computing metabolic module completeness and complementarity
Project-URL: Homepage, https://github.com/NeLLi-team/moducomp
Project-URL: Repository, https://github.com/NeLLi-team/moducomp
Project-URL: Documentation, https://github.com/NeLLi-team/moducomp/blob/main/README.md
Project-URL: Bug Tracker, https://github.com/NeLLi-team/moducomp/issues
Author-email: "Juan C. Villada" <jvillada@lbl.gov>
License: BSD 3-Clause License
License-File: LICENSE.txt
Keywords: bioinformatics,kegg,metabolic,microbiome,modules
Classifier: Development Status :: 4 - Beta
Classifier: Intended Audience :: Science/Research
Classifier: License :: OSI Approved :: MIT License
Classifier: Operating System :: POSIX :: Linux
Classifier: Programming Language :: Python :: 3
Classifier: Programming Language :: Python :: 3.9
Classifier: Programming Language :: Python :: 3.10
Classifier: Programming Language :: Python :: 3.11
Classifier: Topic :: Scientific/Engineering :: Bio-Informatics
Requires-Python: <3.12,>=3.9
Requires-Dist: click~=8.0.0
Requires-Dist: eggnog-mapper<2.2.0,>=2.1.9
Requires-Dist: kegg-pathways-completeness>=1.0.0
Requires-Dist: pandas<2.3,>=1.5
Requires-Dist: typer<0.10.0,>=0.9.1
